setup.cfg
setup.py
abl.errorreporter.egg-info/PKG-INFO
abl.errorreporter.egg-info/SOURCES.txt
abl.errorreporter.egg-info/dependency_links.txt
abl.errorreporter.egg-info/not-zip-safe
abl.errorreporter.egg-info/requires.txt
abl.errorreporter.egg-info/top_level.txt
errorreporter/__init__.py
errorreporter/collector.py
errorreporter/formatter.py
errorreporter/reporter.py
errorreporter/util/__init__.py
errorreporter/util/escaping.py
errorreporter/util/serial_number_generator.py
errorreporter/util/source_encoding.py
tests/__init__.py
tests/test_excser.py