Metadata-Version: 1.0
Name: abl.errorreporter
Version: 0.3
Summary: Lightweight exception recorder, cli part of WebError
Home-page: UNKNOWN
Author: Diez B. Roggisch
Author-email: diez.roggisch@ableton.com
License: UNKNOWN
Platform: UNKNOWN
Classifier: Development Status :: 5 - Production/Stable
Classifier: License :: OSI Approved :: MIT License
Classifier: Operating System :: OS Independent
Classifier: Programming Language :: Python
Classifier: Intended Audience :: Developers
